sharepyle/__init__.py
sharepyle/creds.py
sharepyle/entities.py
sharepyle/helpers.py
sharepyle/listener.py
sharepyle/models.py
sharepyle-1.2.8.dist-info/WHEEL
sharepyle-1.2.8.dist-info/METADATA
sharepyle-1.2.8.dist-info/RECORD
