Metadata-Version: 2.1
Name: sharepyle
Version: 1.2.8
Summary: 
Author: Ryan O'Rourke
Author-email: ryan.orourke@welocalize.com
Requires-Python: >=3.8,<4.0
Classifier: Programming Language :: Python :: 3
Classifier: Programming Language :: Python :: 3.10
Classifier: Programming Language :: Python :: 3.8
Classifier: Programming Language :: Python :: 3.9
Requires-Dist: PyYAML (>=6.0,<7.0)
Requires-Dist: bs4 (>=0.0.1,<0.0.2)
Requires-Dist: dateparser (>=1.0.0,<2.0.0)
Requires-Dist: dpath (>=2.0.1,<3.0.0)
Requires-Dist: fuzzywuzzy (>=0.18.0,<0.19.0)
Requires-Dist: http-requester (>=1.0.11,<2.0.0)
Requires-Dist: pydantic (>=1.6.1,<2.0.0)
Requires-Dist: python-Levenshtein (>=0.12.0,<0.13.0)
Requires-Dist: requests (>=2.24.0,<3.0.0)
